<annotation>
	<folder>wework logo</folder>
	<filename>41718230_873688462833238_5710942600544924353_n.jpg</filename>
	<path>/home/afzal/wework logo/41718230_873688462833238_5710942600544924353_n.jpg</path>
	<source>
		<database>Unknown</database>
	</source>
	<size>
		<width>1080</width>
		<height>1080</height>
		<depth>3</depth>
	</size>
	<segmented>0</segmented>
	<object>
		<name>wework</name>
		<pose>Unspecified</pose>
		<truncated>0</truncated>
		<difficult>0</difficult>
		<bndbox>
			<xmin>454</xmin>
			<ymin>675</ymin>
			<xmax>614</xmax>
			<ymax>752</ymax>
		</bndbox>
	</object>
</annotation>
