<annotation>
	<folder>wework logo</folder>
	<filename>480x300.jpg</filename>
	<path>/home/afzal/wework logo/480x300.jpg</path>
	<source>
		<database>Unknown</database>
	</source>
	<size>
		<width>480</width>
		<height>300</height>
		<depth>3</depth>
	</size>
	<segmented>0</segmented>
	<object>
		<name>wework</name>
		<pose>Unspecified</pose>
		<truncated>0</truncated>
		<difficult>0</difficult>
		<bndbox>
			<xmin>28</xmin>
			<ymin>10</ymin>
			<xmax>65</xmax>
			<ymax>21</ymax>
		</bndbox>
	</object>
</annotation>
